Workbook
Name Slicer_Category: #N/A
Name Slicer_Customer_Segment: #N/A
Name Slicer_Region: #N/A

Sheet Pivot_tables
A3: Product Category by Sales | B3: Sum of Sales
A4: Office Supplies | B4: 1166187
A5: Technology | B5: 1137321.2
A6: Furniture | B6: 1034504.4
A7: Grand Total | B7: 3338012.7
A12: Monthly Sales Trend | B12: Sum of Sales
A13: January | B13: 263914.72
A14: February | B14: 244175.76
A15: March | B15: 272204.49
A16: April | B16: 307549.59
A17: May | B17: 229997.17
A18: June | B18: 335516.89
A19: July | B19: 304087.68
A20: August | B20: 270511.85
A21: September | B21: 260970.3
A22: October | B22: 340837.2
A23: November | B23: 207266.2
A24: December | B24: 300980.82
A25: Grand Total | B25: 3338012.7
A30: Profit By Region | B30: Sum of Profit
A31: West | B31: 293207.87
A32: North | B32: 287555.17
A33: East | B33: 224131.96
A34: South | B34: 222750.46
A35: Grand Total | B35: 1027645.5
A40: Top Products by Sales | B40: Sum of Sales
A41: Notebook | B41: 230381.76
A42: Stapler | B42: 230903.6
A43: Cabinet | B43: 249914.98
A44: Paper Pack | B44: 249984.66
A45: Pen Set | B45: 258206.91
A46: Grand Total | B46: 1219391.9

Sheet Project_1_Ecommerce_Sales_Datas
A1: Ecommerce Sales Performance Dashboard
A4: Interactive dashboard analyzing revenue trends, profitability, regional performance, and product insights.
B7: TOTAL REVENUE | E7: TOTAL PROFIT | H7: TOTAL ORDER | K7: Average Order Value | N7: PROFIT MARGIN
B10: =SUM(Sales_Data!L2:L1001) -> 3338012.7 | E10: =SUM(Sales_Data!N2:N1001) -> 1027645.5 | H10: =COUNTA(Sales_Data!A2:A1001) -> 1000 | K10: =KPIs!A2/KPIs!C2 -> 3338.0127 | N10: =KPIs!E2 -> 0.30786146

Sheet Sales_Data
A1: Order_ID | B1: Order_Date | C1: Month | D1: Customer_ID | E1: Customer_Name | F1: Customer_Segment | G1: Region | H1: Category | I1: Product_Name | J1: Quantity | K1: Unit_Price | L1: Sales | M1: Discount | N1: Profit | O1: Payment_Method | P1: Shipping_Days
A2: ORD-1001 | B2: 2025-02-22 | C2: =TEXT(B2,"MMMM") -> February | D2: CUST-273 | E2: Jordan Valenzuela | F2: Home Office | G2: North | H2: Office Supplies | I2: Notebook | J2: 1 | K2: 895.03 | L2: 895.03 | M2: 0.05 | N2: 391.74 | O2: Bank Transfer | P2: 7
A3: ORD-1002 | B3: 2025-10-15 | C3: =TEXT(B3,"MMMM") -> October | D3: CUST-150 | E3: Sophia Conley | F3: Home Office | G3: West | H3: Technology | I3: Laptop | J3: 2 | K3: 277.99 | L3: 555.98 | M3: 0.2 | N3: 137.52 | O3: Card | P3: 8
A4: ORD-1003 | B4: 2025-06-24 | C4: =TEXT(B4,"MMMM") -> June | D4: CUST-171 | E4: Mary Fernandez | F4: Consumer | G4: South | H4: Office Supplies | I4: Paper Pack | J4: 1 | K4: 915.39 | L4: 915.39 | M4: 0.05 | N4: 235.44 | O4: PayPal | P4: 2
A5: ORD-1004 | B5: 2025-01-23 | C5: =TEXT(B5,"MMMM") -> January | D5: CUST-286 | E5: Mark Collins | F5: Corporate | G5: North | H5: Technology | I5: Mouse | J5: 2 | K5: 443.6 | L5: 887.2 | M5: 0.1 | N5: 246.34 | O5: PayPal | P5: 2
A6: ORD-1005 | B6: 2025-12-27 | C6: =TEXT(B6,"MMMM") -> December | D6: CUST-117 | E6: Chelsea Smith | F6: Consumer | G6: South | H6: Office Supplies | I6: Paper Pack | J6: 10 | K6: 1064.83 | L6: 10648.3 | M6: 0.1 | N6: 3057.69 | O6: PayPal | P6: 2
A7: ORD-1006 | B7: 2025-03-25 | C7: =TEXT(B7,"MMMM") -> March | D7: CUST-194 | E7: Juan Anderson PhD | F7: Corporate | G7: South | H7: Technology | I7: Laptop | J7: 7 | K7: 348.01 | L7: 2436.07 | M7: 0.3 | N7: 368.94 | O7: Bank Transfer | P7: 5
A8: ORD-1007 | B8: 2025-03-25 | C8: =TEXT(B8,"MMMM") -> March | D8: CUST-218 | E8: Christopher Eaton | F8: Corporate | G8: East | H8: Office Supplies | I8: Notebook | J8: 10 | K8: 769.27 | L8: 7692.7 | M8: 0.2 | N8: 1589.92 | O8: Bank Transfer | P8: 9
A9: ORD-1008 | B9: 2025-01-17 | C9: =TEXT(B9,"MMMM") -> January | D9: CUST-180 | E9: Kaylee Ellis | F9: Corporate | G9: East | H9: Technology | I9: Printer | J9: 6 | K9: 1014.57 | L9: 6087.42 | M9: 0 | N9: 2790.36 | O9: Card | P9: 4
A10: ORD-1009 | B10: 2025-11-26 | C10: =TEXT(B10,"MMMM") -> November | D10: CUST-217 | E10: Taylor Soto | F10: Consumer | G10: East | H10: Office Supplies | I10: Paper Pack | J10: 4 | K10: 793.42 | L10: 3173.68 | M10: 0.15 | N10: 529.08 | O10: Card | P10: 4
A11: ORD-1010 | B11: 2025-10-26 | C11: =TEXT(B11,"MMMM") -> October | D11: CUST-202 | E11: Michael Jones | F11: Corporate | G11: South | H11: Office Supplies | I11: Marker Set | J11: 9 | K11: 330.04 | L11: 2970.36 | M11: 0.2 | N11: 899.73 | O11: Card | P11: 9
A12: ORD-1011 | B12: 2025-12-15 | C12: =TEXT(B12,"MMMM") -> December | D12: CUST-208 | E12: Lindsey Aguilar | F12: Home Office | G12: North | H12: Furniture | I12: Office Chair | J12: 1 | K12: 1036.1 | L12: 1036.1 | M12: 0.05 | N12: 294.33 | O12: PayPal | P12: 7
A13: ORD-1012 | B13: 2025-01-06 | C13: =TEXT(B13,"MMMM") -> January | D13: CUST-274 | E13: Jennifer Perez | F13: Home Office | G13: North | H13: Office Supplies | I13: Stapler | J13: 9 | K13: 316.67 | L13: 2850.03 | M13: 0.2 | N13: 468.97 | O13: Bank Transfer | P13: 9
... A1001: ORD-2000 | B1001: 2025-12-18 | C1001: =TEXT(B1001,"MMMM") -> December | D1001: CUST-283 | E1001: George Gomez | F1001: Corporate | G1001: West | H1001: Furniture | I1001: Conference Table | J1001: 7 | K1001: 1108.37 | L1001: 7758.59 | M1001: 0.1 | N1001: 3357.41 | O1001: Card | P1001: 10

Sheet KPIs
A1: Total Revenue | B1: Total Profit | C1: Total Orders | D1: Average Order Value | E1: Profit Margin
A2: =SUM(Sales_Data!L2:L1001) -> 3338012.7 | B2: =SUM(Sales_Data!N2:N1001) -> 1027645.5 | C2: =COUNTA(Sales_Data!A2:A1001) -> 1000 | D2: =A2/C2 -> 3338.0127 | E2: =B2/A2 -> 0.30786146

Sheet Data_Dictionary
A1: Column_Name | B1: Description
A2: Order_ID | B2: Unique identifier for each order
A3: Order_Date | B3: Date customer placed the order
A4: Customer_ID | B4: Unique customer identifier
A5: Customer_Name | B5: Customer full name
A6: Customer_Segment | B6: Customer business segment
A7: Region | B7: Sales region
A8: Category | B8: Product category
A9: Product_Name | B9: Specific product purchased
A10: Quantity | B10: Number of units purchased
A11: Unit_Price | B11: Price per unit
A12: Sales | B12: Total sales amount
... A16: Shipping_Days | B16: Number of days taken for shipping

Sheet Suggested_KPIs
A1: KPI | B1: Purpose
A2: Total Revenue | B2: Measures overall sales performance
A3: Total Profit | B3: Tracks profitability
A4: Profit Margin | B4: Evaluates business efficiency
A5: Total Orders | B5: Tracks transaction volume
A6: Average Order Value | B6: Measures customer spending behavior
